{
  "info": {
    "_postman_id": "eeded8a9-4824-4577-8806-c20e909029d0",
    "name": "springBoot",
    "schema": "https://schema.getpostman.com/json/collection/v2.1.0/collection.json",
    "_exporter_id": "17677106"
  },
  "item": [
    {
      "name": "New Request",
      "request": {
        "method": "GET",
        "header": []
      },
      "response": []
    },
    {
      "name": "AddGuest",
      "request": {
        "method": "POST",
        "header": [],
        "body": {
          "mode": "raw",
          "raw": "{\r\n    \"firstName\": \"Sribatsa\",\r\n    \"lastName\": \"Pradhan\",\r\n    \"emailAddress\": \"carmstrong2p@cyberchimps.com\",\r\n    \"address\": \"4514 Independence Point\",\r\n    \"country\": \"United States\",\r\n    \"state\": \"TX\",\r\n    \"phoneNumber\": \"3-(411)160-3757\"\r\n}",
          "options": {
            "raw": {
              "language": "json"
            }
          }
        },
        "url": {
          "raw": "http://localhost:8080/api/guests",
          "protocol": "http",
          "host": [
            "localhost"
          ],
          "port": "8080",
          "path": [
            "api",
            "guests"
          ],
          "query": [
            {
              "key": "firstName",
              "value": "Sribatsa",
              "type": "text",
              "disabled": true
            },
            {
              "key": "lastName",
              "value": "Pradhan",
              "type": "text",
              "disabled": true
            },
            {
              "key": "phoneNumber",
              "value": "3-(411)160-3757",
              "type": "text",
              "disabled": true
            }
          ]
        }
      },
      "response": []
    },
    {
      "name": "AddRoom",
      "request": {
        "method": "POST",
        "header": [],
        "body": {
          "mode": "raw",
          "raw": "{\r\n    \"name\": \"Sribatsa\",\r\n    \"roomNumber\": \"S1\",\r\n    \"bedInfo\": \"1Q\"\r\n}",
          "options": {
            "raw": {
              "language": "json"
            }
          }
        },
        "url": {
          "raw": "http://localhost:8080/api/rooms",
          "protocol": "http",
          "host": [
            "localhost"
          ],
          "port": "8080",
          "path": [
            "api",
            "rooms"
          ],
          "query": [
            {
              "key": "firstName",
              "value": "Sribatsa",
              "type": "text",
              "disabled": true
            },
            {
              "key": "lastName",
              "value": "Pradhan",
              "type": "text",
              "disabled": true
            },
            {
              "key": "phoneNumber",
              "value": "3-(411)160-3757",
              "type": "text",
              "disabled": true
            }
          ]
        }
      },
      "response": []
    },
    {
      "name": "create-case-template",
      "request": {
        "method": "POST",
        "header": [],
        "body": {
          "mode": "raw",
          "raw": "{\"caseNo\": \"123462\",\r\n    \"orgId\": \"123\",\r\n    \"pod\": \"NA1\",\r\n    \"runtimeEnvironment\": \"AgentSri\",\r\n    \"OSFamily\": \"Linux\",\r\n    \"issue\": \"Process Server in error state\",\r\n    \"description\": \"Test me\",\r\n    \"observation\": \"Address already bind.\"}",
          "options": {
            "raw": {
              "language": "json"
            }
          }
        },
        "url": {
          "raw": "http://localhost:8081/api/template/case",
          "protocol": "http",
          "host": [
            "localhost"
          ],
          "port": "8081",
          "path": [
            "api",
            "template",
            "case"
          ],
          "query": [
            {
              "key": "firstName",
              "value": "Sribatsa",
              "type": "text",
              "disabled": true
            },
            {
              "key": "lastName",
              "value": "Pradhan",
              "type": "text",
              "disabled": true
            },
            {
              "key": "phoneNumber",
              "value": "3-(411)160-3757",
              "type": "text",
              "disabled": true
            }
          ]
        }
      },
      "response": []
    },
    {
      "name": "create-engagement-template",
      "request": {
        "method": "POST",
        "header": [],
        "body": {
          "mode": "raw",
          "raw": "{\"number\": \"ENG-00135\",\r\n    \"name\": \"Technical Onboarding - Cloud Integration\",\r\n    \"account\": \"Risk Management Agency\",\r\n    \"runtimeEnvironment\": \"AgentSri\",\r\n    \"description\": \"NNB Customer and they have questions regarding the secure agent setup and the technical onboarding of the customer. Federal account so they have concerns on their data security and questions may arise regarding the same. Use case and objective Customer is looking to modernize small PowerCenter footprint to IDMC. This customer does not mandate FedRamp and is able to migrate to commercial cloud. Customer is looking to migrate a few workflows and utilize Address Verification in the cloud vs. their current workload with on-prem address verification.\",\r\n    \"csaComments\": \"Go on a call\",\r\n    \"closingNotes\": \"NA\"}",
          "options": {
            "raw": {
              "language": "json"
            }
          }
        },
        "url": {
          "raw": "http://localhost:8081/api/template/engagement",
          "protocol": "http",
          "host": [
            "localhost"
          ],
          "port": "8081",
          "path": [
            "api",
            "template",
            "engagement"
          ],
          "query": [
            {
              "key": "firstName",
              "value": "Sribatsa",
              "type": "text",
              "disabled": true
            },
            {
              "key": "lastName",
              "value": "Pradhan",
              "type": "text",
              "disabled": true
            },
            {
              "key": "phoneNumber",
              "value": "3-(411)160-3757",
              "type": "text",
              "disabled": true
            }
          ]
        }
      },
      "response": []
    }
  ]
}